{
	"configurations" : 
	[
		{
			"directories" : 
			[
				{
					"build" : ".",
					"childIndexes" : 
					[
						1
					],
					"minimumCMakeVersion" : 
					{
						"string" : "3.5.1"
					},
					"projectIndex" : 0,
					"source" : "."
				},
				{
					"build" : "test",
					"minimumCMakeVersion" : 
					{
						"string" : "3.5.1"
					},
					"parentIndex" : 0,
					"projectIndex" : 0,
					"source" : "test",
					"targetIndexes" : 
					[
						0
					]
				}
			],
			"name" : "Debug",
			"projects" : 
			[
				{
					"directoryIndexes" : 
					[
						0,
						1
					],
					"name" : "StaticString",
					"targetIndexes" : 
					[
						0
					]
				}
			],
			"targets" : 
			[
				{
					"directoryIndex" : 1,
					"id" : "tests::@36f028580bb02cc8272a",
					"jsonFile" : "target-tests-Debug-c179bfca49047c1dd5ec.json",
					"name" : "tests",
					"projectIndex" : 0
				}
			]
		}
	],
	"kind" : "codemodel",
	"paths" : 
	{
		"build" : "C:/weasel/deps/boost_1_76_0/libs/static_string/out/build/x64-Debug",
		"source" : "C:/weasel/deps/boost_1_76_0/libs/static_string"
	},
	"version" : 
	{
		"major" : 2,
		"minor" : 2
	}
}
